{
    "gluon": {
        "repository": "freifunk-gluon/gluon",
        "branch": "main",
        "commit": "10728bc8a8ae53f0de8e78ef26497b3aa8826b5a"
    },
    "container": {
        "version": "main"
    },
    "build": {
        "targets": [
            "armsr-armv7",
            "armsr-armv8",
            "ath79-generic",
            "ath79-nand",
            "ipq40xx-generic",
            "lantiq-xrx200",
            "lantiq-xway",
            "mediatek-filogic",
            "mediatek-mt7622",
            "mpc85xx-p1010",
            "mpc85xx-p1020",
            "ramips-mt7620",
            "ramips-mt7621",
            "ramips-mt76x8",
            "rockchip-armv8",
            "x86-64",
            "x86-generic",
            "x86-geode"
        ]
    }
}
